setup.cfg
setup.py
aqara/__init__.py
aqara/client.py
aqara/const.py
aqara/device.py
aqara/gateway.py
aqara/protocol.py
pyaqara.egg-info/PKG-INFO
pyaqara.egg-info/SOURCES.txt
pyaqara.egg-info/dependency_links.txt
pyaqara.egg-info/requires.txt
pyaqara.egg-info/top_level.txt