Metadata-Version: 1.1
Name: pyaqara
Version: 0.21.0
Summary: Python API for interfacing with the Aqara gateway
Home-page: https://github.com/javefang/pyaqara
Author: Xinghong Fang
Author-email: xinghong.fang@gmail.com
License: MIT
Download-URL: https://github.com/javefang/pyaqara/tarball/0.21.0
Keywords: aqara,home,automation,sensor
Platform: UNKNOWN
